{
  "departures": [
    {
      "time": "16:34",
      "destination": "LĘBORK"
    },
    {
      "time": "16:37",
      "destination": "GDAŃSK ŚRÓDMIEŚCIE"
    },
    {
      "time": "16:41",
      "destination": "GDYNIA CISOWA"
    },
    {
      "time": "16:45",
      "destination": "GDAŃSK ŚRÓDMIEŚCIE"
    },
    {
      "time": "16:49",
      "destination": "WEJHEROWO"
    },
    {
      "time": "16:52",
      "destination": "GDAŃSK ŚRÓDMIEŚCIE"
    },
    {
      "time": "16:56",
      "destination": "WEJHEROWO"
    },
    {
      "time": "17:00",
      "destination": "GDAŃSK ŚRÓDMIEŚCIE"
    },
    {
      "time": "17:04",
      "destination": "WEJHEROWO"
    },
    {
      "time": "17:07",
      "destination": "GDAŃSK ŚRÓDMIEŚCIE"
    }
  ]
}