{
  "departures": [
    {
      "time": "18:25",
      "destination": "GDAŃSK ŚRÓDMIEŚCIE"
    },
    {
      "time": "18:29",
      "destination": "GDYNIA CISOWA"
    },
    {
      "time": "18:35",
      "destination": "GDAŃSK ŚRÓDMIEŚCIE"
    },
    {
      "time": "18:39",
      "destination": "WEJHEROWO"
    },
    {
      "time": "18:45",
      "destination": "GDAŃSK ŚRÓDMIEŚCIE"
    },
    {
      "time": "18:49",
      "destination": "GDYNIA CISOWA"
    },
    {
      "time": "18:55",
      "destination": "GDAŃSK ŚRÓDMIEŚCIE"
    },
    {
      "time": "18:59",
      "destination": "LĘBORK"
    },
    {
      "time": "19:05",
      "destination": "GDAŃSK ŚRÓDMIEŚCIE"
    },
    {
      "time": "19:09",
      "destination": "GDYNIA CHYLONIA"
    }
  ]
}