{
  "departures": [
    {
      "time": "17:00",
      "destination": "GDAŃSK ŚRÓDMIEŚCIE"
    },
    {
      "time": "17:04",
      "destination": "WEJHEROWO"
    },
    {
      "time": "17:07",
      "destination": "GDAŃSK ŚRÓDMIEŚCIE"
    },
    {
      "time": "17:11",
      "destination": "WEJHEROWO"
    },
    {
      "time": "17:15",
      "destination": "GDAŃSK ŚRÓDMIEŚCIE"
    },
    {
      "time": "17:19",
      "destination": "WEJHEROWO"
    },
    {
      "time": "17:25",
      "destination": "GDAŃSK ŚRÓDMIEŚCIE"
    },
    {
      "time": "17:26",
      "destination": "GDYNIA CHYLONIA"
    },
    {
      "time": "17:34",
      "destination": "WEJHEROWO"
    },
    {
      "time": "17:35",
      "destination": "GDAŃSK ŚRÓDMIEŚCIE"
    }
  ]
}